helldiver/__init__.py
helldiver/helldiver.py
helldiver-0.1.6.dist-info/WHEEL
helldiver-0.1.6.dist-info/METADATA
helldiver-0.1.6.dist-info/RECORD
